riprova/__init__.py
riprova/async_retrier.py
riprova/backoff.py
riprova/constants.py
riprova/errors.py
riprova/exceptions.py
riprova/retrier.py
riprova/retry.py
riprova/strategies/__init__.py
riprova/strategies/constant.py
riprova/strategies/exponential.py
riprova/strategies/fibonacci.py
riprova-0.3.1.dist-info/LICENSE
riprova-0.3.1.dist-info/METADATA
riprova-0.3.1.dist-info/WHEEL
riprova-0.3.1.dist-info/top_level.txt
riprova-0.3.1.dist-info/RECORD
